{
  "solution": {
    "ember-sortable": {
      "impact": "patch",
      "oldVersion": "5.3.3",
      "newVersion": "5.3.4",
      "tagName": "latest",
      "constraints": [
        {
          "impact": "patch",
          "reason": "Appears in changelog section :bug: Bug Fix"
        }
      ],
      "pkgJSONPath": "./addon/package.json"
    }
  },
  "description": "## Release (2026-06-09)\n\n* ember-sortable 5.3.4 (patch)\n\n#### :bug: Bug Fix\n* `ember-sortable`\n  * [#672](https://github.com/adopted-ember-addons/ember-sortable/pull/672) Remove @embroider/macros ([@NullVoxPopuli](https://github.com/NullVoxPopuli))\n  * [#655](https://github.com/adopted-ember-addons/ember-sortable/pull/655) Drag start: be defensive around sortableGroup.prepare() ([@tniezurawski](https://github.com/tniezurawski))\n\n#### :house: Internal\n* [#673](https://github.com/adopted-ember-addons/ember-sortable/pull/673) update release-plan ([@NullVoxPopuli](https://github.com/NullVoxPopuli))\n\n#### Committers: 2\n- Tomek Nieżurawski ([@tniezurawski](https://github.com/tniezurawski))\n- [@NullVoxPopuli](https://github.com/NullVoxPopuli)\n"
}
